datapackage_pipelines_fiscal/VERSION
datapackage_pipelines_fiscal/__init__.py
datapackage_pipelines_fiscal/generator.py
datapackage_pipelines_fiscal/schema.json
datapackage_pipelines_fiscal/flows/__init__.py
datapackage_pipelines_fiscal/flows/denormalized.py
datapackage_pipelines_fiscal/flows/dimension.py
datapackage_pipelines_fiscal/flows/dump_for_openspending.py
datapackage_pipelines_fiscal/flows/dumper.py
datapackage_pipelines_fiscal/flows/finalize_datapackage.py
datapackage_pipelines_fiscal/flows/normalized.py
datapackage_pipelines_fiscal/flows/utils.py
datapackage_pipelines_fiscal/processors/__init__.py
datapackage_pipelines_fiscal/processors/cleanup-dependencies.py
datapackage_pipelines_fiscal/processors/collect-fiscal-years.py
datapackage_pipelines_fiscal/processors/consts.py
datapackage_pipelines_fiscal/processors/create_babbage_model.py
datapackage_pipelines_fiscal/processors/model.py
datapackage_pipelines_fiscal/processors/normalise_currencies.py
datapackage_pipelines_fiscal/processors/normalise_measures.py
datapackage_pipelines_fiscal/processors/split_per_fiscal_year.py
datapackage_pipelines_fiscal/processors/update_model_in_registry.py
datapackage_pipelines_fiscal/processors/helpers/__init__.py
datapackage_pipelines_fiscal/processors/helpers/enumerate.py
datapackage_pipelines_fiscal/processors/helpers/fix_null_pks.py
datapackage_pipelines_fiscal/processors/helpers/load_primarykey.py
datapackage_pipelines_fiscal/processors/helpers/save_primarykey.py
datapackage_pipelines_fiscal-1.2.7.dist-info/LICENSE.md
datapackage_pipelines_fiscal-1.2.7.dist-info/METADATA
datapackage_pipelines_fiscal-1.2.7.dist-info/WHEEL
datapackage_pipelines_fiscal-1.2.7.dist-info/top_level.txt
datapackage_pipelines_fiscal-1.2.7.dist-info/RECORD
