Metadata-Version: 2.1
Name: datapackage-pipelines-fiscal
Version: 1.2.7
Summary: Fiscal Data Package extensions for Datapackage Pipelines
Home-page: https://github.com/openspending/datapackage-pipelines-fiscal
Author: Open Knowledge International
Author-email: info@okfn.org
License: MIT
Keywords: data
Platform: UNKNOWN
Classifier: Development Status :: 4 - Beta
Classifier: Environment :: Web Environment
Classifier: Intended Audience :: Developers
Classifier: License :: OSI Approved :: MIT License
Classifier: Operating System :: OS Independent
Classifier: Programming Language :: Python :: 3.6
Classifier: Topic :: Internet :: WWW/HTTP :: Dynamic Content
Classifier: Topic :: Software Development :: Libraries :: Python Modules
Requires-Dist: six (>=1.9)
Requires-Dist: datapackage-pipelines (<3,>=2.0.0)
Requires-Dist: datapackage-pipelines-aws
Requires-Dist: datapackage (>=1.0.2)
Requires-Dist: os-package-registry (>=0.0.19)
Provides-Extra: develop
Requires-Dist: tox ; extra == 'develop'
